media_archon/__about__.py
media_archon/__init__.py
media_archon/__main__.py
media_archon/cli.py
media_archon/walker.py
media_archon-0.1.4.dist-info/entry_points.txt
media_archon-0.1.4.dist-info/WHEEL
media_archon-0.1.4.dist-info/METADATA
media_archon-0.1.4.dist-info/licenses/LICENSE
media_archon-0.1.4.dist-info/RECORD
