Metadata-Version: 2.1
Name: media-archon
Version: 0.1.4
Summary: Mirror a directory tree of media files, converting the files to a new format if newer or missing
License: AGPL-3.0-or-later
Author-email: Matthew Swabey <matthew@swabey.org>
Requires-Python: >=3.9
Classifier: Development Status :: 4 - Beta
Classifier: Environment :: Console
Classifier: Intended Audience :: End Users/Desktop
Classifier: Operating System :: MacOS :: MacOS X
Classifier: Operating System :: POSIX :: BSD
Classifier: Operating System :: POSIX :: Linux
Classifier: Operating System :: Unix
Classifier: Programming Language :: Python :: 3
Classifier: Programming Language :: Python :: 3.10
Classifier: Programming Language :: Python :: 3.9
Classifier: Topic :: Multimedia
Classifier: Topic :: Multimedia :: Sound/Audio :: Conversion
Classifier: Topic :: Multimedia :: Video :: Conversion
Classifier: Topic :: Software Development :: Build Tools
Requires-Dist: attrs>=21.4.0
Requires-Dist: cattrs>=22.1.0
Requires-Dist: click>=8.1.3
Requires-Dist: tomli>=2.0.1
Project-URL: Homepage, https://github.com/mattaw/media-archon
Project-URL: media-archon.toml, https://raw.githubusercontent.com/mattaw/media-archon/main/media-archon.toml
